{
    "bbrs": "bestRoundScore",
    "bksk": "BestKillStreak",
    "bmap": "BestRoundMap",
    "cacp": "captureAssists",
    "cdsc": "comanderScore",
    "cmsc": "combatScore",
    "cpcp": "captures",
    "deth": "deaths",
    "dfcp": "defends",
    "dkas": "driverKillAssists",
    "dsab": "driverspecials",
    "dtpm": "deathsPM",
    "dtpr": "deathsPR",
    "fkit": "favKit",
    "fmap": "favMap",
    "fveh": "favVehicle",
    "fwea": "favWeapon",
    "heal": "heals",
    "jond": "joinDate",
    "kick": "kicks",
    "kila": "killassists",
    "kill": "kills",
    "klpm": "killsPM",
    "klpr": "killsPR",
    "klsc": "killScore",
    "loss": "losses",
    "osaa": "weaponAccuracy",
    "ospm": "scorePM",
    "pkas": "killAssistsAP",
    "rpar": "repairs",
    "rsup": "resupplies",
    "rviv": "revives",
    "scor": "score",
    "smoc": "isMajorOfCorps",
    "suic": "suicides",
    "tcdr": "commandTime",
    "tsql": "squadLeaderTime",
    "tsqm": "squadMemberTime",
    "tlwf": "loneWolfTime",
    "tgte": "targetedEnemys",
    "time": "totalTime",
    "topr": "topOponentIR",
    "tvcr": "topVictimIR",
    "twsc": "teamworkScore",
    "wdsk": "worstDeathStreak",
    "wins": "wins",
    "lbtl": "lastPlayTime",
    "vacc": "vehicleAccuracy",
    "tkil": "teamkills",
    "tdmg": "teamDamages",
    "tvdm": "teamVehicleDamages",
    "vrk": "roadKills",
    "mvns": "topVictimName",
    "mvrs": "topVictimRank",
    "mvks": "topVictimKills",
    "vmns": "topOpponentName",
    "vmrs": "topOpponentRank",
    "vmks": "topOpponentKills"
}